farfetch/__init__.py
farfetch/catalogs.py
farfetch/converter.py
farfetch/covers.py
farfetch/images.py
farfetch/keys.py
farfetch/monitor.py
farfetch/network.py
farfetch/products.py
farfetch/repository.py
farfetch/task.py
farfetch/trace_tools.py
farfetch/transmitter.py
modules/__init__.py
modules_for_mozia-1.1.0.dist-info/DESCRIPTION.rst
modules_for_mozia-1.1.0.dist-info/METADATA
modules_for_mozia-1.1.0.dist-info/RECORD
modules_for_mozia-1.1.0.dist-info/WHEEL
modules_for_mozia-1.1.0.dist-info/metadata.json
modules_for_mozia-1.1.0.dist-info/top_level.txt
scheduler/__init__.py
scheduler/scheudler.py
tools/__init__.py
tools/common.py
tools/translate.py
